csv_mAP_calculator/__init__.py
csv_mAP_calculator/compute_overlap_slow.py
csv_mAP_calculator-0.1.3.dist-info/LICENSE
csv_mAP_calculator-0.1.3.dist-info/METADATA
csv_mAP_calculator-0.1.3.dist-info/WHEEL
csv_mAP_calculator-0.1.3.dist-info/top_level.txt
csv_mAP_calculator-0.1.3.dist-info/RECORD
