Metadata-Version: 2.1
Name: csv-mAP-calculator
Version: 0.1.3
Summary: Calculate mAP for CSV format detection result
Home-page: https://https://gitee.com/zhao_qy/csv_mAP_calculator
Author: Autumn
Author-email: zhao_qyu@163.com
License: MIT
Platform: UNKNOWN
Classifier: Programming Language :: Python :: 3
Classifier: Programming Language :: Python :: 3.5
Classifier: Programming Language :: Python :: 3.5
Classifier: Programming Language :: Python :: 3.6
Classifier: Programming Language :: Python :: 3.7
Classifier: Programming Language :: Python :: Implementation :: CPython
Requires-Dist: numpy
Requires-Dist: pandas
Requires-Dist: cython
